{
  "meta": {
    "generated_at": "2026-04-12T20:40:30.911669+00:00",
    "source_file": "/root/.openclaw/workspace/alerts/state/auction_tracking.json",
    "version": "STEP_91B_HARDENED",
    "raw_count": 14,
    "filtered_count": 8,
    "filter_criteria": {
      "min_gap": 12.0,
      "max_bids": 50,
      "required_trust": [
        "HIGH",
        "MEDIUM"
      ],
      "valid_categories": [
        "\ud83d\udd25 High opportunity",
        "\u26a0\ufe0f Watch"
      ],
      "required_product_type": "booster_box",
      "min_baseline": 50,
      "excluded_title_terms": [
        "elite trainer box",
        "elite trainer",
        "etb",
        "booster packs",
        "booster pack",
        "36x",
        "36 packs",
        "36 pack",
        "loose pack",
        "loose packs",
        "sleeved pack",
        "sleeved packs",
        "half booster",
        "half box",
        "1/2 box",
        "half of",
        "display",
        "display box",
        "8x",
        "double pack",
        "dp-",
        "dp06",
        "dp-06",
        "case",
        "booster case",
        "booster box case",
        "collection box",
        "collection boxes",
        "ex collection",
        "v collection",
        "premium collection",
        "special collection",
        "booster bundle",
        "bundle",
        "lot of",
        "lots",
        "mixed",
        "variety",
        "multi",
        "assorted",
        "bulk",
        "s-chinese",
        "schinese",
        "chinese",
        "korean",
        "german",
        "french",
        "italian",
        "spanish",
        "japanese",
        "jp ",
        "jpn ",
        "jp booster",
        "jpn booster",
        "build & battle",
        "build and battle",
        "prerelease",
        "pre-release",
        "tins",
        "blister",
        "blisters",
        "3-pack",
        "3 pack",
        "triple pack",
        "tin ",
        " tin"
      ],
      "excluded_whole_word_terms": [
        "tin",
        "lot"
      ]
    }
  },
  "auctions": [
    {
      "title": "2024 Pokemon Scarlet & Violet Twilight Masquerade Factory Sealed Booster Box",
      "current_price": 132.5,
      "shipping_cost": 14.95,
      "total_price": 147.45,
      "baseline": 336.97,
      "gapPct": 56.24239546547171,
      "bids": 13,
      "time_remaining": 27.399112710555556,
      "opportunity_type": "ongoing",
      "url": "https://www.ebay.com/itm/377098122010?_skw=Pokemon+Twilight+Masquerade+booster+box&hash=item57ccccb31a:g:aRoAAeSwr5Fp1qap",
      "franchise": "pokemon",
      "set": "Twilight Masquerade",
      "product_type": "booster_box",
      "seller_trust": "HIGH",
      "opportunity_score": 75,
      "deal_quality": "high"
    },
    {
      "title": "Pok\u00e9mon TCG Scarlet Violet Destined Rivals Booster Box Factory Sealed SV10",
      "current_price": 229.5,
      "shipping_cost": 17.43,
      "total_price": 246.93,
      "baseline": 594.97,
      "gapPct": 58.49706707901239,
      "bids": 8,
      "time_remaining": 53.602494083611106,
      "opportunity_type": "early",
      "url": "https://www.ebay.com/itm/198263083559?_skw=Pokemon+Destined+Rivals+booster+box&hash=item2e29669227:g:2vkAAeSwcqNpDOqv",
      "franchise": "pokemon",
      "set": "Destined Rivals",
      "product_type": "booster_box",
      "seller_trust": "HIGH",
      "opportunity_score": 75,
      "deal_quality": "high"
    },
    {
      "title": "Pok\u00e9mon TCG Scarlet Violet Twilight Masquerade Booster Box Factory Sealed SV06",
      "current_price": 102.5,
      "shipping_cost": 17.43,
      "total_price": 119.93,
      "baseline": 336.97,
      "gapPct": 64.4092945959581,
      "bids": 18,
      "time_remaining": 53.604668243055556,
      "opportunity_type": "early",
      "url": "https://www.ebay.com/itm/206195918811?_skw=Pokemon+Twilight+Masquerade+booster+box&hash=item30023c07db:g:Z6IAAeSwxT1o2YqO",
      "franchise": "pokemon",
      "set": "Twilight Masquerade",
      "product_type": "booster_box",
      "seller_trust": "HIGH",
      "opportunity_score": 70,
      "deal_quality": "high"
    },
    {
      "title": "\u2728\ufe0fPok\u00e9mon Scarlet & Violet Temporal Forces Booster Box SEALED w/ Acrylic \ud83d\udd25",
      "current_price": 152.5,
      "shipping_cost": 12.0,
      "total_price": 164.5,
      "baseline": 289.42,
      "gapPct": 43.16218644184922,
      "bids": 20,
      "time_remaining": 58.2511686175,
      "opportunity_type": "early",
      "url": "https://www.ebay.com/itm/157818507535?_skw=Pokemon+Temporal+Forces+booster+box&hash=item24beb7510f:g:-xQAAeSwKrhp1c2d",
      "franchise": "pokemon",
      "set": "Temporal Forces",
      "product_type": "booster_box",
      "seller_trust": "HIGH",
      "opportunity_score": 63,
      "deal_quality": "medium"
    },
    {
      "title": "Pokemon Scarlet & Violet Destined Rivals Booster Box #XZI",
      "current_price": 405.0,
      "shipping_cost": 9.99,
      "total_price": 414.99,
      "baseline": 594.97,
      "gapPct": 30.25026471922954,
      "bids": 8,
      "time_remaining": 30.219160778611112,
      "opportunity_type": "ongoing",
      "url": "https://www.ebay.com/itm/198224862290?_skw=Pokemon+Destined+Rivals+booster+box&hash=item2e271f5c52:g:-EAAAeSw7SVpxBQL",
      "franchise": "pokemon",
      "set": "Destined Rivals",
      "product_type": "booster_box",
      "seller_trust": "HIGH",
      "opportunity_score": 57,
      "deal_quality": "medium"
    },
    {
      "title": "Pokemon Scarlet & Violet Destined Rivals Booster Box #ARC",
      "current_price": 425.0,
      "shipping_cost": 9.99,
      "total_price": 434.99,
      "baseline": 594.97,
      "gapPct": 26.888750693312268,
      "bids": 15,
      "time_remaining": 30.00249411777778,
      "opportunity_type": "ongoing",
      "url": "https://www.ebay.com/itm/198224862279?_skw=Pokemon+Destined+Rivals+booster+box&hash=item2e271f5c47:g:4GAAAeSwd6NpxBPH",
      "franchise": "pokemon",
      "set": "Destined Rivals",
      "product_type": "booster_box",
      "seller_trust": "HIGH",
      "opportunity_score": 46,
      "deal_quality": "medium"
    },
    {
      "title": "2025 Pokemon Scarlet & Violet Destined Rivals Factory Sealed Booster Box",
      "current_price": 425.0,
      "shipping_cost": 14.95,
      "total_price": 439.95,
      "baseline": 594.97,
      "gapPct": 26.055095214884787,
      "bids": 11,
      "time_remaining": 27.702494114166665,
      "opportunity_type": "ongoing",
      "url": "https://www.ebay.com/itm/377098122107?_skw=Pokemon+Destined+Rivals+booster+box&hash=item57ccccb37b:g:aNoAAeSwYytp1qY3",
      "franchise": "pokemon",
      "set": "Destined Rivals",
      "product_type": "booster_box",
      "seller_trust": "HIGH",
      "opportunity_score": 46,
      "deal_quality": "medium"
    },
    {
      "title": "2025 Pokemon Scarlet & Violet Destined Rivals Factory Sealed Booster Box",
      "current_price": 455.0,
      "shipping_cost": 14.95,
      "total_price": 469.95,
      "baseline": 594.97,
      "gapPct": 21.01282417600888,
      "bids": 20,
      "time_remaining": 28.113605235555553,
      "opportunity_type": "ongoing",
      "url": "https://www.ebay.com/itm/127799503480?_skw=Pokemon+Destined+Rivals+booster+box&hash=item1dc171aa78:g:zEUAAeSwM~Rp1qa5",
      "franchise": "pokemon",
      "set": "Destined Rivals",
      "product_type": "booster_box",
      "seller_trust": "HIGH",
      "opportunity_score": 41,
      "deal_quality": "medium"
    }
  ]
}