{
  "meta": {
    "generated_at": "2026-04-27T09:24:22.380865+00:00",
    "source_file": "/root/.openclaw/workspace/alerts/state/auction_tracking.json",
    "version": "STEP_91B_HARDENED",
    "raw_count": 27,
    "filtered_count": 12,
    "filter_criteria": {
      "min_gap": 12.0,
      "max_bids": 50,
      "required_trust": [
        "HIGH",
        "MEDIUM"
      ],
      "valid_categories": [
        "\ud83d\udd25 High opportunity",
        "\u26a0\ufe0f Watch"
      ],
      "required_product_type": "booster_box",
      "min_baseline": 50,
      "excluded_title_terms": [
        "elite trainer box",
        "elite trainer",
        "etb",
        "booster packs",
        "booster pack",
        "36x",
        "36 packs",
        "36 pack",
        "loose pack",
        "loose packs",
        "sleeved pack",
        "sleeved packs",
        "half booster",
        "half box",
        "1/2 box",
        "half of",
        "display",
        "display box",
        "8x",
        "double pack",
        "dp-",
        "dp06",
        "dp-06",
        "case",
        "booster case",
        "booster box case",
        "collection box",
        "collection boxes",
        "ex collection",
        "v collection",
        "premium collection",
        "special collection",
        "booster bundle",
        "bundle",
        "lot of",
        "lots",
        "mixed",
        "variety",
        "multi",
        "assorted",
        "bulk",
        "s-chinese",
        "schinese",
        "chinese",
        "korean",
        "german",
        "french",
        "italian",
        "spanish",
        "japanese",
        "jp ",
        "jpn ",
        "jp booster",
        "jpn booster",
        "build & battle",
        "build and battle",
        "prerelease",
        "pre-release",
        "tins",
        "blister",
        "blisters",
        "3-pack",
        "3 pack",
        "triple pack",
        "tin ",
        " tin"
      ],
      "excluded_whole_word_terms": [
        "tin",
        "lot"
      ]
    }
  },
  "auctions": [
    {
      "title": "2024 Pokemon Scarlet & Violet Temporal Forces Factory Sealed Booster Box",
      "current_price": 117.5,
      "shipping_cost": 14.95,
      "total_price": 132.45,
      "baseline": 294.83,
      "gapPct": 55.07580639690669,
      "bids": 15,
      "time_remaining": 15.131444211944444,
      "opportunity_type": "ongoing",
      "url": "https://www.ebay.com/itm/377134315830?_skw=Pokemon+Temporal+Forces+booster+box&hash=item57cef4f936:g:HaYAAeSw0Ulp6SlE",
      "franchise": "pokemon",
      "set": "Temporal Forces",
      "product_type": "booster_box",
      "seller_trust": "HIGH",
      "opportunity_score": 80,
      "deal_quality": "high"
    },
    {
      "title": "One Piece TCG - OP09 Emperors in the New World Booster Box English - SEALED New",
      "current_price": 362.66,
      "shipping_cost": 33.83,
      "total_price": 396.49,
      "baseline": 646.98,
      "gapPct": 38.716807320164456,
      "bids": 8,
      "time_remaining": 34.09620779805556,
      "opportunity_type": "ongoing",
      "url": "https://www.ebay.com/itm/168316524593?_skw=One+Piece+Emperors+in+the+New+World+booster+box&hash=item2730725831:g:E6cAAeSwpNlphyvs",
      "franchise": "onepiece",
      "set": "Emperors in the New World",
      "product_type": "booster_box",
      "seller_trust": "MEDIUM",
      "opportunity_score": 66,
      "deal_quality": "medium"
    },
    {
      "title": "Pokemon Scarlet & Violet Destined Rivals Booster Box #EKE",
      "current_price": 200.5,
      "shipping_cost": 9.99,
      "total_price": 210.49,
      "baseline": 585.54,
      "gapPct": 64.05198620077194,
      "bids": 27,
      "time_remaining": 64.63896599416667,
      "opportunity_type": "early",
      "url": "https://www.ebay.com/itm/198291966699?_skw=Pokemon+Destined+Rivals+booster+box&hash=item2e2b1f4aeb:g:83kAAeSwLGBp48H~",
      "franchise": "pokemon",
      "set": "Destined Rivals",
      "product_type": "booster_box",
      "seller_trust": "HIGH",
      "opportunity_score": 65,
      "deal_quality": "medium"
    },
    {
      "title": "One Piece Card Game - OP07 Booster Box English 500 Years in the Future - Sealed",
      "current_price": 178.62,
      "shipping_cost": 33.83,
      "total_price": 212.45,
      "baseline": 335.0,
      "gapPct": 36.58208955223881,
      "bids": 7,
      "time_remaining": 34.09864614027778,
      "opportunity_type": "ongoing",
      "url": "https://www.ebay.com/itm/168316339496?_skw=One+Piece+500+Years+in+the+Future+booster+box&hash=item27306f8528:g:-vcAAeSwjoxphygA",
      "franchise": "onepiece",
      "set": "500 Years in the Future",
      "product_type": "booster_box",
      "seller_trust": "MEDIUM",
      "opportunity_score": 64,
      "deal_quality": "medium"
    },
    {
      "title": "One Piece TCG - OP09 Emperors in the New World Booster Box English - SEALED New",
      "current_price": 410.52,
      "shipping_cost": 33.83,
      "total_price": 444.34999999999997,
      "baseline": 646.98,
      "gapPct": 31.31936072212434,
      "bids": 10,
      "time_remaining": 10.26287448611111,
      "opportunity_type": "ending_soon",
      "url": "https://www.ebay.com/itm/168314063920?_skw=One+Piece+Emperors+in+the+New+World+booster+box&hash=item27304ccc30:g:E6cAAeSwpNlphyvs",
      "franchise": "onepiece",
      "set": "Emperors in the New World",
      "product_type": "booster_box",
      "seller_trust": "MEDIUM",
      "opportunity_score": 63,
      "deal_quality": "medium"
    },
    {
      "title": "2024 Pokemon Scarlet & Violet Temporal Forces Factory Sealed Booster Box",
      "current_price": 200.0,
      "shipping_cost": 14.95,
      "total_price": 214.95,
      "baseline": 294.83,
      "gapPct": 27.09357935081233,
      "bids": 19,
      "time_remaining": 15.064777554722223,
      "opportunity_type": "ongoing",
      "url": "https://www.ebay.com/itm/377134315829?_skw=Pokemon+Temporal+Forces+booster+box&hash=item57cef4f935:g:sq8AAeSwLqJp6Sf8",
      "franchise": "pokemon",
      "set": "Temporal Forces",
      "product_type": "booster_box",
      "seller_trust": "HIGH",
      "opportunity_score": 52,
      "deal_quality": "medium"
    },
    {
      "title": "Pokemon TCG Scarlet & Violet Twilight Masquerade Booster Box SEALED/NEW",
      "current_price": 212.5,
      "shipping_cost": 16.0,
      "total_price": 228.5,
      "baseline": 339.61,
      "gapPct": 32.71694001943406,
      "bids": 21,
      "time_remaining": 40.62505203083333,
      "opportunity_type": "ongoing",
      "url": "https://www.ebay.com/itm/389920502384?_skw=Pokemon+Twilight+Masquerade+booster+box&hash=item5ac912b270:g:unwAAeSwBXRp59f6",
      "franchise": "pokemon",
      "set": "Twilight Masquerade",
      "product_type": "booster_box",
      "seller_trust": "HIGH",
      "opportunity_score": 50,
      "deal_quality": "medium"
    },
    {
      "title": "One Piece Card Game - OP07 Booster Box English 500 Years in the Future - Sealed",
      "current_price": 217.95,
      "shipping_cost": 33.83,
      "total_price": 251.77999999999997,
      "baseline": 335.0,
      "gapPct": 24.841791044776127,
      "bids": 11,
      "time_remaining": 10.098646143888889,
      "opportunity_type": "ending_soon",
      "url": "https://www.ebay.com/itm/168314062255?_skw=One+Piece+500+Years+in+the+Future+booster+box&hash=item27304cc5af:g:-vcAAeSwjoxphygA",
      "franchise": "onepiece",
      "set": "500 Years in the Future",
      "product_type": "booster_box",
      "seller_trust": "MEDIUM",
      "opportunity_score": 49,
      "deal_quality": "medium"
    },
    {
      "title": "Pokemon TCG Scarlet & Violet Temporal Forces Booster Box SEALED/NEW",
      "current_price": 217.5,
      "shipping_cost": 18.0,
      "total_price": 235.5,
      "baseline": 294.83,
      "gapPct": 20.12346097751246,
      "bids": 11,
      "time_remaining": 18.277555318611114,
      "opportunity_type": "ongoing",
      "url": "https://www.ebay.com/itm/366358639970?_skw=Pokemon+Temporal+Forces+booster+box&hash=item554cad3562:g:aRgAAeSwhkpp5mar",
      "franchise": "pokemon",
      "set": "Temporal Forces",
      "product_type": "booster_box",
      "seller_trust": "HIGH",
      "opportunity_score": 45,
      "deal_quality": "medium"
    },
    {
      "title": "Pok\u00e9mon TCG Scarlet & Violet Temporal Forces Booster Box Factory Sealed SV05",
      "current_price": 222.5,
      "shipping_cost": 0.0,
      "total_price": 222.5,
      "baseline": 294.83,
      "gapPct": 24.53278160295763,
      "bids": 15,
      "time_remaining": 40.850055313333336,
      "opportunity_type": "ongoing",
      "url": "https://www.ebay.com/itm/287280749962?_skw=Pokemon+Temporal+Forces+booster+box&hash=item42e3445d8a:g:FfgAAeSw27Bp5DV5",
      "franchise": "pokemon",
      "set": "Temporal Forces",
      "product_type": "booster_box",
      "seller_trust": "HIGH",
      "opportunity_score": 44,
      "deal_quality": "medium"
    },
    {
      "title": "One Piece TCG OP-09 Emperors In The New World Booster Box SEALED NEW English",
      "current_price": 520.0,
      "shipping_cost": 0.0,
      "total_price": 520.0,
      "baseline": 646.98,
      "gapPct": 19.62657269158243,
      "bids": 2,
      "time_remaining": 61.31870782527778,
      "opportunity_type": "early",
      "url": "https://www.ebay.com/itm/227312721714?_skw=One+Piece+Emperors+in+the+New+World+booster+box&hash=item34ece4df32:g:494AAeSwTU5p6U6X",
      "franchise": "onepiece",
      "set": "Emperors in the New World",
      "product_type": "booster_box",
      "seller_trust": "HIGH",
      "opportunity_score": 44,
      "deal_quality": "medium"
    },
    {
      "title": "Pokemon TCG Scarlet & Violet Temporal Forces Booster Box SEALED/NEW",
      "current_price": 217.5,
      "shipping_cost": 16.0,
      "total_price": 233.5,
      "baseline": 294.83,
      "gapPct": 20.801817996811717,
      "bids": 13,
      "time_remaining": 40.62755531055555,
      "opportunity_type": "ongoing",
      "url": "https://www.ebay.com/itm/366360921238?_skw=Pokemon+Temporal+Forces+booster+box&hash=item554cd00496:g:oyUAAeSwcCJp59g0",
      "franchise": "pokemon",
      "set": "Temporal Forces",
      "product_type": "booster_box",
      "seller_trust": "HIGH",
      "opportunity_score": 40,
      "deal_quality": "medium"
    }
  ]
}