{
  "timestamp": "2026-05-20T22:03:04.403593+00:00",
  "tier": "free",
  "deal": {
    "title": "Pokemon Destined Rivals Booster Box 36 packs, New & Sealed LIVE ONLY",
    "price": 442.02,
    "shipping_cost": 62.64,
    "total_price": 504.65999999999997,
    "url": "https://www.ebay.com/itm/287286257363?_skw=pokemon+Destined+Rivals+booster+box&hash=item42e39866d3:g:FwoAAeSwW15puZ4T",
    "seller_rating": 99.9,
    "seller_feedback_count": 953,
    "franchise": "pokemon",
    "set": "Destined Rivals",
    "set_code": null,
    "language": "EN",
    "product_type": "booster_box",
    "variant": "standard",
    "confidence": "high",
    "baseline_price": 620.0,
    "baseline_raw_count": 49,
    "baseline_pre_filter_count": 37,
    "baseline_final_count": 19,
    "baseline_raw_min": 138.0,
    "baseline_raw_max": 3899.99,
    "gapPct": 18.6,
    "shipping_verified": true,
    "_source": "starter_pokemon"
  },
  "selection_reason": "mid_tier_deal_gap_18.6pct",
  "next_refresh_hours": 4,
  "total_safe_deals_available": 3,
  "_refresh_locked": false,
  "_next_refresh_in_hours": 4
}