{
  "timestamp": "2026-05-10T05:02:54.322826+00:00",
  "tier": "free",
  "deal": {
    "title": "Pokemon TCG Sword & Shield Battle Styles Booster Box SEALED NEW",
    "price": 269.99,
    "shipping_cost": 0.0,
    "total_price": 269.99,
    "url": "https://www.ebay.com/itm/389953682447?_skw=pokemon+Battle+Styles+booster+box&hash=item5acb0cfc0f:g:-WoAAeSwzJ1p8kGE",
    "seller_rating": 100.0,
    "seller_feedback_count": 228,
    "franchise": "pokemon",
    "set": "Battle Styles",
    "set_code": null,
    "language": "EN",
    "product_type": "booster_box",
    "variant": "standard",
    "confidence": "medium",
    "baseline_price": 300.0,
    "baseline_raw_count": 34,
    "baseline_pre_filter_count": 32,
    "baseline_final_count": 19,
    "baseline_raw_min": 259.95,
    "baseline_raw_max": 2049.99,
    "gapPct": 10.0,
    "shipping_verified": false,
    "_source": "starter_pokemon"
  },
  "selection_reason": "mid_tier_deal_gap_10.0pct",
  "next_refresh_hours": 4,
  "total_safe_deals_available": 5,
  "_refresh_locked": true,
  "_next_refresh_in_hours": 3
}