{
  "timestamp": "2026-04-01T21:34:06.096181+00:00",
  "tier": "starter",
  "total_deals": 5,
  "all_deals_count": 5,
  "summary_counts": {
    "by_franchise": {
      "pokemon": 2,
      "onepiece": 3
    },
    "by_product_type": {
      "booster_box": 5
    },
    "by_gap_bucket": {
      "20_plus": 2,
      "10_to_19": 2,
      "1_to_9": 1
    }
  },
  "trust_counts": {
    "HIGH": 5,
    "MEDIUM": 0,
    "LOW": 0
  },
  "available_filters": {
    "franchise": [
      "onepiece",
      "pokemon"
    ],
    "set": [
      "Adventure on Kami's Island",
      "Emperors in the New World",
      "500 Years in the Future",
      "Battle Styles",
      "Destined Rivals"
    ],
    "product_type": [
      "booster_box"
    ],
    "gap_bucket": [
      "20_plus",
      "10_to_19",
      "1_to_9"
    ]
  },
  "deals": [
    {
      "title": "Pokemon Destined Rivals 36 Factory Sealed Booster Packs! Booster Box of Packs!",
      "price": 449.99,
      "shipping_cost": 0.0,
      "total_price": 449.99,
      "url": "https://www.ebay.com/itm/177795952773?_skw=Destined+Rivals+japanese+booster+box&hash=item296576f085:g:BAAAAeSwivJpcOhF",
      "seller_rating": 99.3,
      "seller_feedback_count": 1136,
      "franchise": "pokemon",
      "set": "Destined Rivals",
      "set_code": null,
      "language": "EN",
      "product_type": "booster_box",
      "variant": "standard",
      "confidence": "high",
      "baseline_price": 600.0,
      "baseline_raw_count": 55,
      "baseline_pre_filter_count": 40,
      "baseline_final_count": 26,
      "baseline_raw_min": 86.53,
      "baseline_raw_max": 4000.0,
      "gapPct": 25.0,
      "shipping_verified": true
    },
    {
      "title": "Battle Styles Booster Box Factory Sealed Sword & Shield Pokemon",
      "price": 258.7,
      "shipping_cost": 17.63,
      "total_price": 276.33,
      "url": "https://www.ebay.com/itm/297998490837?_skw=pokemon+Battle+Styles+booster+box&hash=item4562181cd5:g:hegAAeSwedFpgpxA",
      "seller_rating": 100.0,
      "seller_feedback_count": 602,
      "franchise": "pokemon",
      "set": "Battle Styles",
      "set_code": null,
      "language": "EN",
      "product_type": "booster_box",
      "variant": "standard",
      "confidence": "high",
      "baseline_price": 312.5,
      "baseline_raw_count": 32,
      "baseline_pre_filter_count": 31,
      "baseline_final_count": 20,
      "baseline_raw_min": 258.7,
      "baseline_raw_max": 2950.0,
      "gapPct": 11.57,
      "shipping_verified": true
    },
    {
      "title": "One Piece Card Game OP-09 Emperors in the New World Booster Box English | SEALED",
      "price": 423.26,
      "shipping_cost": 42.43,
      "total_price": 465.69,
      "url": "https://www.ebay.com/itm/318090915826?_skw=onepiece+Emperors+in+the+New+World+booster+box&hash=item4a0fb22ff2:g:09gAAeSwzEppY9S6",
      "seller_rating": 100.0,
      "seller_feedback_count": 4466,
      "franchise": "onepiece",
      "set": "Emperors in the New World",
      "set_code": "OP-09",
      "language": "EN",
      "product_type": "booster_box",
      "variant": "standard_box",
      "confidence": "low",
      "baseline_price": 614.99,
      "baseline_raw_count": 64,
      "baseline_pre_filter_count": 47,
      "baseline_final_count": 31,
      "baseline_raw_min": 115.41,
      "baseline_raw_max": 9999.99,
      "gapPct": 24.28,
      "shipping_verified": true
    },
    {
      "title": "One Piece OP- 07 500 Years In The Future Booster Box NEW SEALED INHAND",
      "price": 238.09,
      "shipping_cost": 36.04,
      "total_price": 274.13,
      "url": "https://www.ebay.com/itm/236576367257?_skw=onepiece+500+Years+in+the+Future+sealed&hash=item37150ce299:g:9vsAAeSw5ItpY5~-",
      "seller_rating": 100.0,
      "seller_feedback_count": 631,
      "franchise": "onepiece",
      "set": "500 Years in the Future",
      "set_code": null,
      "language": "EN",
      "product_type": "booster_box",
      "variant": "standard_box",
      "confidence": "low",
      "baseline_price": 334.16,
      "baseline_raw_count": 49,
      "baseline_pre_filter_count": 38,
      "baseline_final_count": 22,
      "baseline_raw_min": 83.99,
      "baseline_raw_max": 4999.99,
      "gapPct": 17.96,
      "shipping_verified": true
    },
    {
      "title": "OP-15 Adventure on KAMI\u2019s Island Booster Box JP Sealed One Piece TCG US Seller",
      "price": 95.99,
      "shipping_cost": 0.0,
      "total_price": 95.99,
      "url": "https://www.ebay.com/itm/127667135610?_skw=onepiece+Adventure+on+Kami%27s+Island+booster+box&hash=item1db98de47a:g:az8AAeSwZUpphJN5&amdata=enc%3AAQALAAABEACCtXRWQnOEpyOqnQQ8KGb%2F0gLAoPqtXbtuQJtmN5F2CkCw01UgxhdEI0H1gwymYnwlfTAEhabzAy6H3FNeINLV6APG1JG7Ap4NWeV9PEQlb%2FatX4oHPuFqVHvzV2FU29YhZIwIN7nbcKKf0lIMzPwWdRFKNke63dsxDt7l%2BNORvklhg85eKCqi3zhiKiCl8dg4SDRDF%2B0fmkHnuYOHW3JnWZJ%2BcWMFIJcS9A7sX4E4ioACEGBEk9NEqgsrWM9F2jKce09AyNdYqi%2Frq0C%2BGZhgx32nJ5i%2BxukNnv3EzWpPQhJtuO5krJ%2FZE1A3GOSgX%2FfP3OKKUiZ%2BbV1sASDCeUce7by%2FeCn973Mw8bkdF24g",
      "seller_rating": 99.9,
      "seller_feedback_count": 5256,
      "franchise": "onepiece",
      "set": "Adventure on Kami's Island",
      "set_code": null,
      "language": "JP",
      "product_type": "booster_box",
      "variant": "standard_box",
      "confidence": "low",
      "baseline_price": 105.99,
      "baseline_raw_count": 12,
      "baseline_pre_filter_count": 10,
      "baseline_final_count": 8,
      "baseline_raw_min": 82.63,
      "baseline_raw_max": 134.95,
      "gapPct": 9.43,
      "shipping_verified": true
    }
  ],
  "watchlist_deals": [
    {
      "title": "Pokemon Sword & Shield Battle Styles Booster Box / New Factory Sealed",
      "price": 289.99,
      "shipping_cost": 0.0,
      "total_price": 289.99,
      "url": "https://www.ebay.com/itm/397736542567?_skw=pokemon+Battle+Styles+booster+box&hash=item5c9af20167:g:DQgAAeSwhHdpvE69",
      "seller_rating": 100.0,
      "seller_feedback_count": 294,
      "franchise": "pokemon",
      "set": "Battle Styles",
      "set_code": null,
      "language": "EN",
      "product_type": "booster_box",
      "variant": "standard",
      "confidence": "high",
      "baseline_price": 312.5,
      "baseline_raw_count": 32,
      "baseline_pre_filter_count": 31,
      "baseline_final_count": 20,
      "baseline_raw_min": 258.7,
      "baseline_raw_max": 2950.0,
      "gapPct": 7.2,
      "shipping_verified": true
    },
    {
      "title": "Pokemon TCG: S&V Destined Rivals Factory Sealed Booster Box",
      "price": 549.0,
      "shipping_cost": 10.99,
      "total_price": 559.99,
      "url": "https://www.ebay.com/itm/389566613349?_skw=pokemon+Destined+Rivals+booster+box&hash=item5ab3fac765:g:hKQAAeSwXZFpf8Ng&amdata=enc%3AAQALAAABAACCtXRWQnOEpyOqnQQ8KGZKmt5wg5Goj8HjC6QezbHnWLyjgnfbVGlJoCgycTaAN%2FK2erzLIewFaSWvvFGGgrka1ApujUiHnWbIH4Babd6ARWEV70dGh1nL1T0FjLLnRHVqls73l8NyS2ChSlCrgscwMu7uk0H5SatrfQNJ%2Fr8lCoVBqpU4oSmy2CiyZhSGxvaGFkTpgyO9sTWKAYWhlwYC5EmVku%2BQmxr4SgYZAf9i09muo7tlXXGFjfQkdXQxJhQKzt8QaAjPiyGmJMxWjCRk5EixkTkGpi7RJYFWviwVDRzgTomMUUU4F4tNW%2FG8ZdL66C1VPO6fZZ3eK1dD20o%3D",
      "seller_rating": 99.5,
      "seller_feedback_count": 1986,
      "franchise": "pokemon",
      "set": "Destined Rivals",
      "set_code": null,
      "language": "EN",
      "product_type": "booster_box",
      "variant": "standard",
      "confidence": "high",
      "baseline_price": 600.0,
      "baseline_raw_count": 55,
      "baseline_pre_filter_count": 40,
      "baseline_final_count": 26,
      "baseline_raw_min": 86.53,
      "baseline_raw_max": 4000.0,
      "gapPct": 6.67,
      "shipping_verified": true
    },
    {
      "title": "ONE PIECE OP09 EMPERORS IN THE NEW WORLD SEALED BOOSTER BOX ENGLISH OP-09 OP9 EN",
      "price": 577.53,
      "shipping_cost": 0.0,
      "total_price": 577.53,
      "url": "https://www.ebay.com/itm/197123391268?_skw=onepiece+Emperors+in+the+New+World+booster+box&hash=item2de5783f24:g:b2MAAOSweWpn2aZF",
      "seller_rating": 100.0,
      "seller_feedback_count": 772,
      "franchise": "onepiece",
      "set": "Emperors in the New World",
      "set_code": "OP-09",
      "language": "EN",
      "product_type": "booster_box",
      "variant": "standard_box",
      "confidence": "low",
      "baseline_price": 614.99,
      "baseline_raw_count": 64,
      "baseline_pre_filter_count": 47,
      "baseline_final_count": 31,
      "baseline_raw_min": 115.41,
      "baseline_raw_max": 9999.99,
      "gapPct": 6.09,
      "shipping_verified": true
    }
  ]
}