{
  "timestamp": "2026-03-22T15:02:22.185516+00:00",
  "tier": "starter",
  "total_deals": 5,
  "all_deals_count": 5,
  "summary_counts": {
    "by_franchise": {
      "onepiece": 2,
      "pokemon": 3
    },
    "by_product_type": {
      "booster_box": 4,
      "etb": 1
    },
    "by_gap_bucket": {
      "20_plus": 2,
      "10_to_19": 3
    }
  },
  "trust_counts": {
    "HIGH": 5,
    "MEDIUM": 0,
    "LOW": 0
  },
  "available_filters": {
    "franchise": [
      "onepiece",
      "pokemon"
    ],
    "set": [
      "Awakening of the New Era",
      "Temporal Forces",
      "Twilight Masquerade",
      "Wings of the Captain"
    ],
    "product_type": [
      "booster_box",
      "etb"
    ],
    "gap_bucket": [
      "10_to_19",
      "20_plus"
    ]
  },
  "deals": [
    {
      "title": "One Piece OP-06 Wings Of The Captain Booster Box Factory Sealed English",
      "url": "https://www.ebay.com/itm/177954344166?_skw=one+piece+OP-06+booster+box&hash=item296ee7cce6:g:kVMAAeSweQpps3ER",
      "franchise": "onepiece",
      "set": "Wings of the Captain",
      "product_type": "booster_box",
      "price": 240.12,
      "baseline_price": 350.0,
      "gapPct": 31.39,
      "confidence": "high",
      "gap_bucket": "20_plus",
      "seller_trust": "HIGH"
    },
    {
      "title": "Pokemon TCG Temporal Forces Booster Box 36 Packs Brand New & Factory Sealed!",
      "url": "https://www.ebay.com/itm/177978930861?_skw=pokemon+Temporal+Forces+booster+box&hash=item29705ef6ad:g:wsgAAeSwgidpvnL3",
      "franchise": "pokemon",
      "set": "Temporal Forces",
      "product_type": "booster_box",
      "price": 249.25,
      "baseline_price": 315.0,
      "gapPct": 20.87,
      "confidence": "high",
      "gap_bucket": "20_plus",
      "seller_trust": "HIGH"
    },
    {
      "title": "Scarlet & Violet Twilight Masquerade Elite Trainer Box Pokemon TCG New/Sealed\ud83c\udf43",
      "url": "https://www.ebay.com/itm/376975517013?_skw=pokemon+Twilight+Masquerade+sealed+booster+box&hash=item57c57de555:g:qdkAAeSwI3pplu7i",
      "franchise": "pokemon",
      "set": "Twilight Masquerade",
      "product_type": "etb",
      "price": 72.0,
      "baseline_price": 87.99,
      "gapPct": 18.17,
      "confidence": "high",
      "gap_bucket": "10_to_19",
      "seller_trust": "HIGH"
    },
    {
      "title": "One Piece TCG: Awakening of the New Era Booster Box ENGLISH OP05 FACTORY SEALED",
      "url": "https://www.ebay.com/itm/397547489153?_skw=one+piece+OP-05+booster+box&hash=item5c8fad4781:g:tSAAAeSwqxdpetwp",
      "franchise": "onepiece",
      "set": "Awakening of the New Era",
      "product_type": "booster_box",
      "price": 999.99,
      "baseline_price": 1217.5,
      "gapPct": 17.87,
      "confidence": "high",
      "gap_bucket": "10_to_19",
      "seller_trust": "HIGH"
    },
    {
      "title": "Pokemon Twilight Masquerade Booster Box 36 Packs Sealed (please see photos)",
      "url": "https://www.ebay.com/itm/177977455528?_skw=pokemon+Twilight+Masquerade+booster+box&hash=item29704873a8:g:jBoAAeSwAJlpvbRX",
      "franchise": "pokemon",
      "set": "Twilight Masquerade",
      "product_type": "booster_box",
      "price": 306.84,
      "baseline_price": 350.0,
      "gapPct": 12.33,
      "confidence": "high",
      "gap_bucket": "10_to_19",
      "seller_trust": "HIGH"
    }
  ]
}