{
  "timestamp": "2026-04-27T10:02:53.867190+00:00",
  "non_ebay_stats": {
    "detected": 2,
    "in_output": 2,
    "in_best_deals": 2,
    "in_watchlist": 0
  },
  "tier": "starter",
  "total_deals": 3,
  "all_deals_count": 10,
  "summary_counts": {
    "by_franchise": {
      "onepiece": 1,
      "pokemon": 2
    },
    "by_product_type": {
      "booster_box": 3
    },
    "by_gap_bucket": {
      "10_to_19": 3
    },
    "by_source": {
      "stompinggroundstcg": 1,
      "ebay": 1,
      "gamenerdz": 1
    }
  },
  "trust_counts": {
    "HIGH": 3,
    "MEDIUM": 0,
    "LOW": 0
  },
  "available_filters": {
    "franchise": [
      "onepiece",
      "pokemon"
    ],
    "set": [
      "Adventure on Kami's Island",
      "Battle Styles"
    ],
    "product_type": [
      "booster_box"
    ],
    "gap_bucket": [
      "10_to_19"
    ]
  },
  "deals": [
    {
      "title": "One Piece Adventure on Kami's Island Booster Box [OP-15]",
      "url": "https://stompinggroundstcg.com/products/one-piece-adventure-on-kamis-island-booster-box-op-15",
      "franchise": "onepiece",
      "set": "Adventure on Kami's Island",
      "product_type": "booster_box",
      "price": 189.0,
      "baseline_price": 225.0,
      "gapPct": 16.0,
      "seller_trust": "HIGH",
      "source": "stompinggroundstcg",
      "availability": "unknown",
      "is_preorder": false,
      "language": "EN",
      "shipping_cost": 0,
      "confidence": "high",
      "non_ebay": true,
      "deal_quality": "high",
      "gap_bucket": "10_to_19"
    },
    {
      "title": "Battle Styles Booster Box Pokemon TCG Sword & Shield SWSH05 New Factory Sealed",
      "url": "https://www.ebay.com/itm/397879743099?_skw=pokemon+Battle+Styles+booster+box&hash=item5ca37b127b:g:yAwAAeSwuzJp7OsI",
      "franchise": "pokemon",
      "set": "Battle Styles",
      "product_type": "booster_box",
      "price": 255.0,
      "shipping_cost": 0.0,
      "total_price": 255.0,
      "shipping_verified": true,
      "baseline_price": 299.49,
      "gapPct": 14.86,
      "confidence": "high",
      "seller_rating": 99.9,
      "seller_feedback_count": 1505,
      "language": "EN",
      "source": "ebay",
      "non_ebay": false,
      "seller_trust": "HIGH",
      "deal_quality": "high",
      "gap_bucket": "10_to_19"
    },
    {
      "title": "Pokemon: Sword & Shield - Battle Styles Booster Box",
      "url": "https://www.gamenerdz.com/pokemon-sword-shield-battle-styles-booster-box",
      "franchise": "pokemon",
      "set": "Battle Styles",
      "product_type": "booster_box",
      "price": 269.97,
      "baseline_price": 312.5,
      "gapPct": 13.61,
      "seller_trust": "HIGH",
      "source": "gamenerdz",
      "availability": "in_stock",
      "is_preorder": false,
      "language": "EN",
      "shipping_cost": 0,
      "confidence": "high",
      "non_ebay": true,
      "deal_quality": "high",
      "gap_bucket": "10_to_19"
    }
  ],
  "watchlist_deals": [
    {
      "title": "ONE PIECE Card Game Emperors in the New World OP-09 Booster Box NEW SEALED FS",
      "url": "https://www.ebay.com/itm/196850247770?_skw=onepiece+Emperors+in+the+New+World+booster+box&hash=item2dd530685a:g:XwQAAOSwAUVmyehd&amdata=enc%3AAQALAAABEACCtXRWQnOEpyOqnQQ8KGbAggOqo%2BF9kaDAT%2BgxFIgzavumOUPY2ifte5PJ0n1Gv9%2BUT9%2FFWynddHUq%2Fum2o7swbPtNgbArhyXGW8%2FJeQJxBSd9xULnO7ji8MovqiA%2BevTUWm9K8ok1XHjswJZSBL%2BC2DL8vU7CSmDCS24gJIDxinc3Vd7%2BY%2FvktdX%2B4t5WD%2BlXEv87N74EhjVgxr0pFv5AZeR2lPa3ZbUrW0o0b2HgjLi09GEmih8FQXk%2BVJAg5HjldHi7i6ZhCC%2FsPZw8BH8Yf%2Fgj3pzoi8CKM2UUBYNkRtY1cwmPJ8KFWJpDqWOsIZed%2FMmhB8%2BV1KSv5nGC6fweeCXthb9E9gtF0FlOCUS6",
      "franchise": "onepiece",
      "set": "Emperors in the New World",
      "product_type": "booster_box",
      "price": 282.29,
      "shipping_cost": 49.99,
      "total_price": 282.29,
      "shipping_verified": true,
      "baseline_price": 548.32,
      "gapPct": 48.52,
      "confidence": "medium",
      "seller_rating": 99.6,
      "seller_feedback_count": 459,
      "language": "JP",
      "source": "ebay",
      "non_ebay": false,
      "seller_trust": "HIGH",
      "deal_quality": "medium",
      "gap_bucket": "20_plus",
      "watchlist_reason": "low_confidence",
      "_first_seen_at": "2026-04-27T06:03:17.876777+00:00",
      "_last_seen_at": "2026-04-27T10:02:53.866230+00:00"
    },
    {
      "title": "ONE PIECE OP15 Adventure on KAMI’s Island Booster Box JAPANESE Sealed TCG",
      "url": "https://www.ebay.com/itm/287167294659?_skw=onepiece+Adventure+on+Kami%27s+Island+booster+box&hash=item42dc812cc3:g:bv4AAeSwWflpoPBx&amdata=enc%3AAQALAAABEACCtXRWQnOEpyOqnQQ8KGamODoauNWXU0D4MIdL5y0X7aXQmPYnnsvor%2FlkIYNad4c%2BRDcwFU1kE63O6eeJ0Yar5F6r%2BUk2TvxgEpPiTRefLQr5CdKCv7qgIHxGvbuLN%2Bf9KzCKqB7M%2BG9fWkc%2FA3V6D0KHIcWNkKL7Mdy5%2Fz9gJvbIxZzazf680K5ljJuFJo677oceDoJZbmG1%2FoUYQ77QJovWTbAkfPQgtZBSjFdFoh%2FCBLUG%2FFH8dl%2BgdG9qZc5xlCnvbTEvE6WmRTRzMPkVl2c6Deno6Hh1J7Y07Yz6Lxec%2BQiz8f14%2FDVlJVdgiJjcSzcmuxPUPpOKJ4dmASqd8LtF9pWcRHmiGgEAKoTN",
      "franchise": "onepiece",
      "set": "Adventure on Kami's Island",
      "product_type": "booster_box",
      "price": 134.95,
      "shipping_cost": 0.0,
      "total_price": 134.95,
      "shipping_verified": true,
      "baseline_price": 232.0,
      "gapPct": 41.83,
      "confidence": "medium",
      "seller_rating": 99.2,
      "seller_feedback_count": 432,
      "language": "JP",
      "source": "ebay",
      "non_ebay": false,
      "seller_trust": "HIGH",
      "deal_quality": "medium",
      "gap_bucket": "20_plus",
      "watchlist_reason": "low_confidence",
      "_first_seen_at": "2026-04-27T08:02:48.339227+00:00",
      "_last_seen_at": "2026-04-27T10:02:53.866230+00:00"
    },
    {
      "title": "Pokemon Sword & Shield ASTRAL RADIANCE Booster Box Sealed BRAZILIAN PORTUGUESE",
      "url": "https://www.ebay.com/itm/277578484256?_skw=pokemon+Astral+Radiance+booster+box&hash=item40a0f78a20:g:oB8AAOSwfjNjG-Gd",
      "franchise": "pokemon",
      "set": "Astral Radiance",
      "product_type": "booster_box",
      "price": 314.99,
      "shipping_cost": 39.99,
      "total_price": 314.99,
      "shipping_verified": true,
      "baseline_price": 399.5,
      "gapPct": 21.15,
      "confidence": "medium",
      "seller_rating": 100.0,
      "seller_feedback_count": 3672,
      "language": "EN",
      "source": "ebay",
      "non_ebay": false,
      "seller_trust": "HIGH",
      "deal_quality": "medium",
      "gap_bucket": "20_plus",
      "watchlist_reason": "low_confidence",
      "_first_seen_at": "2026-04-27T08:43:22.871565+00:00",
      "_last_seen_at": "2026-04-27T09:00:01.383277+00:00"
    },
    {
      "title": "Pokemon Rivali Predestinati Box Italian Destined Rivals Booster Box Sealed ",
      "url": "https://www.ebay.com/itm/318207939528?_skw=pokemon+Destined+Rivals+booster+box&hash=item4a16abd3c8:g:vwoAAeSwzmBp7imJ",
      "franchise": "pokemon",
      "set": "Destined Rivals",
      "product_type": "booster_box",
      "price": 499.0,
      "shipping_cost": 0.0,
      "total_price": 499.0,
      "shipping_verified": false,
      "baseline_price": 599.0,
      "gapPct": 16.69,
      "confidence": "medium",
      "seller_rating": 100.0,
      "seller_feedback_count": 2597,
      "language": "EN",
      "source": "ebay",
      "non_ebay": false,
      "seller_trust": "HIGH",
      "deal_quality": "medium",
      "gap_bucket": "10_to_19",
      "watchlist_reason": "low_confidence",
      "_first_seen_at": "2026-04-27T09:23:11.413111+00:00",
      "_last_seen_at": "2026-04-27T10:02:53.866230+00:00"
    },
    {
      "title": "One Piece OP15/EB04 Adventure on KAMI’S Island Booster Box ENGLISH Sealed",
      "url": "https://www.ebay.com/itm/168231442186?_skw=onepiece+Adventure+on+Kami%27s+Island+booster+box&hash=item272b60170a:g:EVoAAeSwhgxptNSQ",
      "franchise": "onepiece",
      "set": "Adventure on Kami's Island",
      "product_type": "booster_box",
      "price": 198.44,
      "shipping_cost": 0.0,
      "total_price": 198.44,
      "shipping_verified": true,
      "baseline_price": 232.5,
      "gapPct": 14.65,
      "confidence": "medium",
      "seller_rating": 99.3,
      "seller_feedback_count": 649364,
      "language": "EN",
      "source": "ebay",
      "non_ebay": false,
      "seller_trust": "HIGH",
      "deal_quality": "medium",
      "gap_bucket": "10_to_19",
      "watchlist_reason": "low_confidence",
      "_first_seen_at": "2026-04-27T02:03:53.643942+00:00",
      "_last_seen_at": "2026-04-27T10:02:53.866230+00:00"
    },
    {
      "title": "Pokemon Sword and Shield Lost Origin Booster Box Sealed",
      "url": "https://www.ebay.com/itm/366371442500?_skw=pokemon+Lost+Origin+booster+box&hash=item554d708f44:g:9ecAAeSwnLZp7ltI",
      "franchise": "pokemon",
      "set": "Lost Origin",
      "product_type": "booster_box",
      "price": 700.0,
      "shipping_cost": 0.0,
      "total_price": 700.0,
      "shipping_verified": false,
      "baseline_price": 813.0,
      "gapPct": 13.9,
      "confidence": "medium",
      "seller_rating": 100.0,
      "seller_feedback_count": 225,
      "language": "EN",
      "source": "ebay",
      "non_ebay": false,
      "seller_trust": "HIGH",
      "deal_quality": "medium",
      "gap_bucket": "10_to_19",
      "watchlist_reason": "low_confidence",
      "_first_seen_at": "2026-04-27T07:23:20.237000+00:00",
      "_last_seen_at": "2026-04-27T08:00:01.490134+00:00"
    },
    {
      "title": "Pokemon Destined Rivals Booster Box Sealed",
      "url": "https://www.ebay.com/itm/168333149382?_skw=pokemon+Destined+Rivals+booster+box&hash=item27317004c6:g:FnEAAeSw8iBp7Ot3",
      "franchise": "pokemon",
      "set": "Destined Rivals",
      "product_type": "booster_box",
      "price": 544.29,
      "shipping_cost": 49.05,
      "total_price": 544.29,
      "shipping_verified": true,
      "baseline_price": 599.0,
      "gapPct": 9.13,
      "confidence": "medium",
      "seller_rating": 100.0,
      "seller_feedback_count": 547,
      "language": "EN",
      "source": "ebay",
      "non_ebay": false,
      "seller_trust": "HIGH",
      "deal_quality": "medium",
      "gap_bucket": "1_to_9",
      "watchlist_reason": "low_confidence",
      "_first_seen_at": "2026-04-27T04:22:49.716985+00:00",
      "_last_seen_at": "2026-04-27T09:00:01.383277+00:00"
    }
  ],
  "empty_watchlist": false,
  "fallback_deals": [],
  "_single_writer_info": {
    "version": "v2.0",
    "ebay_deals": 1,
    "retailer_deals": 3,
    "total_merged": 3,
    "retailer_deals_visible": true
  }
}